EventExtract-1.1.dist-info/METADATA
EventExtract-1.1.dist-info/RECORD
EventExtract-1.1.dist-info/WHEEL
EventExtract-1.1.dist-info/top_level.txt
petrarch2/GetInfo.py
petrarch2/GetInfo2.py
petrarch2/PETRglobals.py
petrarch2/PETRreader.py
petrarch2/PETRtree.py
petrarch2/PETRwriter.py
petrarch2/ParseRoleCode.py
petrarch2/__init__.py
petrarch2/access_solr.py
petrarch2/base_instance.py
petrarch2/constants.py
petrarch2/databasewriter.py
petrarch2/nltk_depends.py
petrarch2/petrarch2.py
petrarch2/petrarch3.py
petrarch2/read_file.py
petrarch2/session_factory.py
petrarch2/setup.py
petrarch2/simpleRegexNER.py
petrarch2/test.py
petrarch2/utilities.py
petrarch2/write_file.py
