Metadata-Version: 2.1
Name: EventExtract
Version: 1.1
Summary: EventExtract
Home-page: http://www.eventanalysis.com.cn:28081/
Author: wzy
Author-email: hawangzy@163.com
Maintainer: wzy
Maintainer-email: hawangzy@163.com
License: BSD License
Platform: all
Classifier: Development Status :: 4 - Beta
Classifier: Operating System :: OS Independent
Classifier: Intended Audience :: Developers
Classifier: License :: OSI Approved :: BSD License
Classifier: Programming Language :: Python
Classifier: Programming Language :: Python :: Implementation
Classifier: Programming Language :: Python :: 2.7
Classifier: Topic :: Software Development :: Libraries
